netbox_otp_plugin/__init__.py
netbox_otp_plugin/forms.py
netbox_otp_plugin/middleware.py
netbox_otp_plugin/models.py
netbox_otp_plugin/navigation.py
netbox_otp_plugin/tables.py
netbox_otp_plugin/urls.py
netbox_otp_plugin/views.py
netbox_otp_plugin/management/commands/addtotp.py
netbox_otp_plugin/management/commands/resettotp.py
netbox_otp_plugin/migrations/0001_initial.py
netbox_otp_plugin/migrations/__init__.py
netbox_otp_plugin/templates/otp_device.html
netbox_otp_plugin/templates/otp_login.html
netbox_otp_plugin/templatetags/__init__.py
netbox_otp_plugin/templatetags/otp_login_helpers.py
netbox_otp_plugin-1.3.4.dist-info/licenses/LICENSE.txt
netbox_otp_plugin-1.3.4.dist-info/METADATA
netbox_otp_plugin-1.3.4.dist-info/WHEEL
netbox_otp_plugin-1.3.4.dist-info/top_level.txt
netbox_otp_plugin-1.3.4.dist-info/RECORD
