Metadata-Version: 2.4
Name: netbox_otp_plugin
Version: 1.3.4
Summary: OTP Login NetBox plugin
Home-page: https://github.com/k1nky/netbox-otp-plugin
Author: Andrey Shalashov
Author-email: avshalashov@yandex.ru
License: Apache 2.0
Keywords: netbox otp login plugin
License-File: LICENSE.txt
Requires-Dist: qrcode
Requires-Dist: django-otp==1.6.3
Requires-Dist: django-qr-code
Dynamic: author
Dynamic: author-email
Dynamic: description-content-type
Dynamic: home-page
Dynamic: keywords
Dynamic: license
Dynamic: license-file
Dynamic: requires-dist
Dynamic: summary
